{
  "variants": {
    "is_tip=false,is_base=false,vertical_direction=down": {
      "model": "toneko:block/pointed_end_rod_middle",
      "x": 180
    },
    "is_tip=false,is_base=false,vertical_direction=up": {
      "model": "toneko:block/pointed_end_rod_middle"
    },

    "is_tip=false,is_base=true,vertical_direction=down": {
      "model": "minecraft:block/end_rod",
      "x": 180
    },
    "is_tip=false,is_base=true,vertical_direction=up": {
      "model": "minecraft:block/end_rod"
    },

    "is_tip=true,is_base=false,vertical_direction=down": {
      "model": "toneko:block/pointed_end_rod_tip",
      "x": 180
    },
    "is_tip=true,is_base=false,vertical_direction=up": {
      "model": "toneko:block/pointed_end_rod_tip"
    },

    "is_tip=true,is_base=true,vertical_direction=down": {
      "model": "toneko:block/pointed_end_rod_base_tip",
      "x": 180
    },
    "is_tip=true,is_base=true,vertical_direction=up": {
      "model": "toneko:block/pointed_end_rod_base_tip"
    }
  }
}